<?xml version="1.0"?>
<profile>
  <key_values>
    <number_followers>  
  40 Followers
</number_followers>
    <number_tweets>  
  50 Tweets
</number_tweets>
    <number_following>  
  419 Following
</number_following>
  </key_values>
  <tweets>
    <tweet tweet_id="360523525456535554">
      <tweet_content>weird! consistently able to repro -- only extension is ad block -- I guess if you're around I'd be happy to demo</tweet_content>
      <retweet_count>0</retweet_count>
      <favourite_count>0</favourite_count>
    </tweet>
    <tweet tweet_id="360009631071870978">
      <tweet_content>what's up with yr media queries? my os x 10.8 chrome 27 is apparently three inch wide phone...</tweet_content>
      <retweet_count>0</retweet_count>
      <favourite_count>0</favourite_count>
    </tweet>
    <tweet tweet_id="358226363146186753">
      <tweet_content>Hacker News needs a "Downvote All" button at the top of every thread.</tweet_content>
      <retweet_count>21</retweet_count>
      <favourite_count>26</favourite_count>
    </tweet>
    <tweet tweet_id="354895967553716225">
      <tweet_content>do you know how invites work? random? time since signup? i've had write access for 3 months but don't know what to write</tweet_content>
      <retweet_count>0</retweet_count>
      <favourite_count>0</favourite_count>
    </tweet>
    <tweet tweet_id="351217996141838339">
      <tweet_content>just doing my part for the open source community, etc.</tweet_content>
      <retweet_count>0</retweet_count>
      <favourite_count>0</favourite_count>
    </tweet>
    <tweet tweet_id="345871161210597377">
      <tweet_content>hilariously this is what tipped stallman over the edge to found GNU</tweet_content>
      <retweet_count>0</retweet_count>
      <favourite_count>0</favourite_count>
    </tweet>
    <tweet tweet_id="342876203012718592">
      <tweet_content>Goddam, Twin Peaks was great.</tweet_content>
      <retweet_count>0</retweet_count>
      <favourite_count>0</favourite_count>
    </tweet>
    <tweet tweet_id="342610582760984576">
      <tweet_content>the road to hell is paved with progress reports and dressing gowns...</tweet_content>
      <retweet_count>0</retweet_count>
      <favourite_count>0</favourite_count>
    </tweet>
    <tweet tweet_id="342174025436516352">
      <tweet_content>well... at least one of us will be right:</tweet_content>
      <retweet_count>2</retweet_count>
      <favourite_count>0</favourite_count>
    </tweet>
    <tweet tweet_id="341525693521330176">
      <tweet_content>cool, new gmail inbox just ticked over at midnight -- was wondering why I got logged out</tweet_content>
      <retweet_count>0</retweet_count>
      <favourite_count>0</favourite_count>
    </tweet>
    <tweet tweet_id="341208159999905792">
      <tweet_content>3am is a pretty annoying time for github to be down</tweet_content>
      <retweet_count>0</retweet_count>
      <favourite_count>0</favourite_count>
    </tweet>
    <tweet tweet_id="340352413653422080">
      <tweet_content>nah it's pretty good</tweet_content>
      <retweet_count>0</retweet_count>
      <favourite_count>0</favourite_count>
    </tweet>
    <tweet tweet_id="335745738241892352">
      <tweet_content>broke my front teeth surfing today and googled it and it said i unlocked my chakras wassup</tweet_content>
      <retweet_count>2</retweet_count>
      <favourite_count>5</favourite_count>
    </tweet>
    <tweet tweet_id="335648428996567040">
      <tweet_content>haha... as though I am going bother turning up to those? the scales don't exactly tip in favour of the (up to) 5% bonus...</tweet_content>
      <retweet_count>0</retweet_count>
      <favourite_count>0</favourite_count>
    </tweet>
    <tweet tweet_id="334793957215203328">
      <tweet_content>know any decent css preprocessor chrome extensions? should try make a flat ui theme</tweet_content>
      <retweet_count>0</retweet_count>
      <favourite_count>0</favourite_count>
    </tweet>
    <tweet tweet_id="333912854895927296">
      <tweet_content>isomorphic to the gradient wrt the buddha nature of a dog; it's all mu to me
(turned out all I need is product, sum and \propto)</tweet_content>
      <retweet_count>0</retweet_count>
      <favourite_count>0</favourite_count>
    </tweet>
    <tweet tweet_id="333899771708317696">
      <tweet_content>trivially we can apply lagrange multipliers, which I leave as an exercise for the reader</tweet_content>
      <retweet_count>0</retweet_count>
      <favourite_count>0</favourite_count>
    </tweet>
    <tweet tweet_id="330950067861192704">
      <tweet_content>it's not as though getting a picture of hindley milner and a t shirt printing service is overly difficult though, surely?</tweet_content>
      <retweet_count>0</retweet_count>
      <favourite_count>0</favourite_count>
    </tweet>
    <tweet tweet_id="330511534109376512">
      <tweet_content>big o brewery? does that mean we can look forward to an n factori-ale (or will that take too long...)</tweet_content>
      <retweet_count>0</retweet_count>
      <favourite_count>0</favourite_count>
    </tweet>
    <tweet tweet_id="330511534109376512">
      <tweet_content>big o brewery? does that mean we can look forward to an n factori-ale (or will that take too long...)</tweet_content>
      <retweet_count>0</retweet_count>
      <favourite_count>0</favourite_count>
    </tweet>
    <tweet tweet_id="330275513291657216">
      <tweet_content>i'm a big fan of 2 &amp;gt;&amp;gt; 32</tweet_content>
      <retweet_count>0</retweet_count>
      <favourite_count>0</favourite_count>
    </tweet>
    <tweet tweet_id="329096107739213824">
      <tweet_content>Great news everybody!  just got support for Node.js error reporting!</tweet_content>
      <retweet_count>5</retweet_count>
      <favourite_count>3</favourite_count>
    </tweet>
    <tweet tweet_id="327309983064678400">
      <tweet_content/>
      <retweet_count>0</retweet_count>
      <favourite_count>0</favourite_count>
    </tweet>
    <tweet tweet_id="326221393945587712">
      <tweet_content>btw have you noticed the footer links from app.raygun io to forums, terms, privacy will 404 and raygun io/forums has untrusted ssl</tweet_content>
      <retweet_count>0</retweet_count>
      <favourite_count>0</favourite_count>
    </tweet>
    <tweet tweet_id="325883948297232384">
      <tweet_content>paper only!? how am I supposed to wget -nd -r -A png,jpg  that?</tweet_content>
      <retweet_count>0</retweet_count>
      <favourite_count>0</favourite_count>
    </tweet>
    <tweet tweet_id="324515764268838914">
      <tweet_content>HTTP is totally fucked</tweet_content>
      <retweet_count>2</retweet_count>
      <favourite_count>0</favourite_count>
    </tweet>
    <tweet tweet_id="323251770916745217">
      <tweet_content>just another relaxing sunday afternoon burp session? weird that the unminified one returns fine though:...</tweet_content>
      <retweet_count>0</retweet_count>
      <favourite_count>0</favourite_count>
    </tweet>
    <tweet tweet_id="323056721029394433">
      <tweet_content/>
      <retweet_count>0</retweet_count>
      <favourite_count>0</favourite_count>
    </tweet>
    <tweet tweet_id="322559218165088256">
      <tweet_content>awesome! looking forward to them : )</tweet_content>
      <retweet_count>0</retweet_count>
      <favourite_count>0</favourite_count>
    </tweet>
    <tweet tweet_id="322558468135469056">
      <tweet_content>hey, are you going to be putting the talks from today online?</tweet_content>
      <retweet_count>0</retweet_count>
      <favourite_count>0</favourite_count>
    </tweet>
    <tweet tweet_id="322556105517576192">
      <tweet_content>Monads? Functors??</tweet_content>
      <retweet_count>8</retweet_count>
      <favourite_count>2</favourite_count>
    </tweet>
    <tweet tweet_id="322470780820656128">
      <tweet_content>What happens to you if you break the monad laws?</tweet_content>
      <retweet_count>16</retweet_count>
      <favourite_count>6</favourite_count>
    </tweet>
    <tweet tweet_id="322097651321552896">
      <tweet_content>There is zero overlap between developers who prefer IPAs and developers who prefer IDEs.</tweet_content>
      <retweet_count>273</retweet_count>
      <favourite_count>102</favourite_count>
    </tweet>
    <tweet tweet_id="321492076556591104">
      <tweet_content>close but no cigar</tweet_content>
      <retweet_count>0</retweet_count>
      <favourite_count>0</favourite_count>
    </tweet>
    <tweet tweet_id="318607744762523648">
      <tweet_content>I looked this up once and according to some random blog comment it's straight vector paths:</tweet_content>
      <retweet_count>0</retweet_count>
      <favourite_count>0</favourite_count>
    </tweet>
    <tweet tweet_id="309070865075695617">
      <tweet_content>On our blog: Of all the ways to spend a summer -  intern    ^JD</tweet_content>
      <retweet_count>5</retweet_count>
      <favourite_count>0</favourite_count>
    </tweet>
    <tweet tweet_id="308776916977082368">
      <tweet_content>The new 'about' dialog in  (dynamically pulled from ). We're excited to watch this grow! --</tweet_content>
      <retweet_count>7</retweet_count>
      <favourite_count>5</favourite_count>
    </tweet>
    <tweet tweet_id="307768930179620864">
      <tweet_content>teach me how to accent</tweet_content>
      <retweet_count>0</retweet_count>
      <favourite_count>0</favourite_count>
    </tweet>
    <tweet tweet_id="303410190810750976">
      <tweet_content>yo i'm doing a blog for work... hit me up with the 140 chars pearls of wisdom and/or email me if you want anything there from you</tweet_content>
      <retweet_count>0</retweet_count>
      <favourite_count>0</favourite_count>
    </tweet>
    <tweet tweet_id="297497675618721792">
      <tweet_content>think  hit the donation mother lode yesterday, finally found a 79 picador crying of lot 49 to complete my  collection</tweet_content>
      <retweet_count>0</retweet_count>
      <favourite_count>0</favourite_count>
    </tweet>
    <tweet tweet_id="296904255175020544">
      <tweet_content>beers, headphones and shitty slides...</tweet_content>
      <retweet_count>0</retweet_count>
      <favourite_count>0</favourite_count>
    </tweet>
    <tweet tweet_id="296863689158574080">
      <tweet_content>practising for yr presentation tmrw?</tweet_content>
      <retweet_count>0</retweet_count>
      <favourite_count>0</favourite_count>
    </tweet>
    <tweet tweet_id="292457584139591682">
      <tweet_content>stop using javascript seriously it doesn't work</tweet_content>
      <retweet_count>35</retweet_count>
      <favourite_count>14</favourite_count>
    </tweet>
    <tweet tweet_id="276975266310537216">
      <tweet_content>Q: How many prolog programmers does it take to change a lightbulb?

A: Yes.</tweet_content>
      <retweet_count>3</retweet_count>
      <favourite_count>0</favourite_count>
    </tweet>
    <tweet tweet_id="269363937361920000">
      <tweet_content>rad, that's what's called instant service. sorry for bugging you over something so obviously trivial. keep up the cool stuff dude!</tweet_content>
      <retweet_count>0</retweet_count>
      <favourite_count>0</favourite_count>
    </tweet>
    <tweet tweet_id="269361851232571392">
      <tweet_content>what's up with bootstrap, specifically github btns, by the looks of it?</tweet_content>
      <retweet_count>0</retweet_count>
      <favourite_count>0</favourite_count>
    </tweet>
    <tweet tweet_id="265610618604756993">
      <tweet_content/>
      <retweet_count>0</retweet_count>
      <favourite_count>0</favourite_count>
    </tweet>
    <tweet tweet_id="255381147788390401">
      <tweet_content>Rather than flog a dead horse, a good Haskeller knows how to abstract over different kinds of beatings, the nature of death, and horsiness.</tweet_content>
      <retweet_count>114</retweet_count>
      <favourite_count>53</favourite_count>
    </tweet>
    <tweet tweet_id="251269579836370944">
      <tweet_content>how can I adjust for timezone? compare  with what my github says (attached)</tweet_content>
      <retweet_count>0</retweet_count>
      <favourite_count>0</favourite_count>
    </tweet>
    <tweet tweet_id="250554398885937152">
      <tweet_content>does this mean crockford's keynote  talk will be online soon?</tweet_content>
      <retweet_count>0</retweet_count>
      <favourite_count>0</favourite_count>
    </tweet>
    <tweet tweet_id="360523525456535554">
      <tweet_content>weird! consistently able to repro -- only extension is ad block -- I guess if you're around I'd be happy to demo</tweet_content>
      <retweet_count>0</retweet_count>
      <favourite_count>0</favourite_count>
    </tweet>
    <tweet tweet_id="360009631071870978">
      <tweet_content>what's up with yr media queries? my os x 10.8 chrome 27 is apparently three inch wide phone...</tweet_content>
      <retweet_count>0</retweet_count>
      <favourite_count>0</favourite_count>
    </tweet>
    <tweet tweet_id="358226363146186753">
      <tweet_content>Hacker News needs a "Downvote All" button at the top of every thread.</tweet_content>
      <retweet_count>21</retweet_count>
      <favourite_count>26</favourite_count>
    </tweet>
    <tweet tweet_id="354895967553716225">
      <tweet_content>do you know how invites work? random? time since signup? i've had write access for 3 months but don't know what to write</tweet_content>
      <retweet_count>0</retweet_count>
      <favourite_count>0</favourite_count>
    </tweet>
    <tweet tweet_id="351217996141838339">
      <tweet_content>just doing my part for the open source community, etc.</tweet_content>
      <retweet_count>0</retweet_count>
      <favourite_count>0</favourite_count>
    </tweet>
    <tweet tweet_id="345871161210597377">
      <tweet_content>hilariously this is what tipped stallman over the edge to found GNU</tweet_content>
      <retweet_count>0</retweet_count>
      <favourite_count>0</favourite_count>
    </tweet>
    <tweet tweet_id="342876203012718592">
      <tweet_content>Goddam, Twin Peaks was great.</tweet_content>
      <retweet_count>0</retweet_count>
      <favourite_count>0</favourite_count>
    </tweet>
    <tweet tweet_id="342610582760984576">
      <tweet_content>the road to hell is paved with progress reports and dressing gowns...</tweet_content>
      <retweet_count>0</retweet_count>
      <favourite_count>0</favourite_count>
    </tweet>
    <tweet tweet_id="342174025436516352">
      <tweet_content>well... at least one of us will be right:</tweet_content>
      <retweet_count>2</retweet_count>
      <favourite_count>0</favourite_count>
    </tweet>
    <tweet tweet_id="341525693521330176">
      <tweet_content>cool, new gmail inbox just ticked over at midnight -- was wondering why I got logged out</tweet_content>
      <retweet_count>0</retweet_count>
      <favourite_count>0</favourite_count>
    </tweet>
    <tweet tweet_id="341208159999905792">
      <tweet_content>3am is a pretty annoying time for github to be down</tweet_content>
      <retweet_count>0</retweet_count>
      <favourite_count>0</favourite_count>
    </tweet>
    <tweet tweet_id="340352413653422080">
      <tweet_content>nah it's pretty good</tweet_content>
      <retweet_count>0</retweet_count>
      <favourite_count>0</favourite_count>
    </tweet>
    <tweet tweet_id="335745738241892352">
      <tweet_content>broke my front teeth surfing today and googled it and it said i unlocked my chakras wassup</tweet_content>
      <retweet_count>2</retweet_count>
      <favourite_count>5</favourite_count>
    </tweet>
    <tweet tweet_id="335648428996567040">
      <tweet_content>haha... as though I am going bother turning up to those? the scales don't exactly tip in favour of the (up to) 5% bonus...</tweet_content>
      <retweet_count>0</retweet_count>
      <favourite_count>0</favourite_count>
    </tweet>
    <tweet tweet_id="334793957215203328">
      <tweet_content>know any decent css preprocessor chrome extensions? should try make a flat ui theme</tweet_content>
      <retweet_count>0</retweet_count>
      <favourite_count>0</favourite_count>
    </tweet>
    <tweet tweet_id="333912854895927296">
      <tweet_content>isomorphic to the gradient wrt the buddha nature of a dog; it's all mu to me
(turned out all I need is product, sum and \propto)</tweet_content>
      <retweet_count>0</retweet_count>
      <favourite_count>0</favourite_count>
    </tweet>
    <tweet tweet_id="333899771708317696">
      <tweet_content>trivially we can apply lagrange multipliers, which I leave as an exercise for the reader</tweet_content>
      <retweet_count>0</retweet_count>
      <favourite_count>0</favourite_count>
    </tweet>
    <tweet tweet_id="330950067861192704">
      <tweet_content>it's not as though getting a picture of hindley milner and a t shirt printing service is overly difficult though, surely?</tweet_content>
      <retweet_count>0</retweet_count>
      <favourite_count>0</favourite_count>
    </tweet>
    <tweet tweet_id="330511534109376512">
      <tweet_content>big o brewery? does that mean we can look forward to an n factori-ale (or will that take too long...)</tweet_content>
      <retweet_count>0</retweet_count>
      <favourite_count>0</favourite_count>
    </tweet>
  </tweets>
</profile>
